ade_enseirb/__init__.py
ade_enseirb/ade.py
ade_enseirb/ade_fetcher.py
ade_enseirb/cas.py
ade_enseirb/utils.py
ade_enseirb-0.1.1.dist-info/LICENSE
ade_enseirb-0.1.1.dist-info/METADATA
ade_enseirb-0.1.1.dist-info/WHEEL
ade_enseirb-0.1.1.dist-info/top_level.txt
ade_enseirb-0.1.1.dist-info/RECORD
